csw93/__init__.py
csw93/data/format_table.py
csw93/data/raw_data/csw_16.txt
csw93/data/raw_data/csw_32.txt
csw93/data/raw_data/csw_64.txt
csw93/data/raw_data/xu_1024.txt
csw93/data/raw_data/xu_128.txt
csw93/data/raw_data/xu_2048.txt
csw93/data/raw_data/xu_256.txt
csw93/data/raw_data/xu_256_2.txt
csw93/data/raw_data/xu_4096.txt
csw93/data/raw_data/xu_512.txt
csw93/data/raw_data/xu_512_2.txt
csw93/data/tables.csv
csw93/defining_relation.py
csw93/main.py
csw93-0.6.0.dist-info/LICENSE
csw93-0.6.0.dist-info/WHEEL
csw93-0.6.0.dist-info/METADATA
csw93-0.6.0.dist-info/RECORD
