Metadata-Version: 2.1
Name: csw93
Version: 0.6.0
Summary: Regular Fractional Factorial two-level designs from the paper of Chen, Sun and Wu (1993)
Home-page: https://abohyndoe.github.io/csw93/
License: MIT
Author: Alexandre Bohyn
Author-email: alexandre.bohyn@kuleuven.be
Requires-Python: >=3.8,<4.0
Classifier: License :: OSI Approved :: MIT License
Classifier: Programming Language :: Python :: 3
Classifier: Programming Language :: Python :: 3.8
Classifier: Programming Language :: Python :: 3.9
Classifier: Programming Language :: Python :: 3.10
Requires-Dist: graphviz (>=0.19.1,<0.20.0)
Requires-Dist: numpy (>=1.22.2,<2.0.0)
Requires-Dist: pandas (>=1.4.0,<2.0.0)
Project-URL: Repository, https://github.com/ABohynDOE/csw93
